{
  "freelancers": [
    {
      "id": 1,
      "name": "John Doe",
      "email": "john@example.com",
      "password": "password",
      "profession": "Web Developer",
      "skills": ["HTML", "CSS", "JavaScript"],
      "hourly_rate": 25,
      "profile_picture": "https://reqres.in/img/faces/7-image.jpg",
      "isBooked": false
    },
    {
      "id": 2,
      "name": "Jane Smith",
      "email": "jane@example.com",
      "password": "password",
      "profession": "Graphic Designer",
      "skills": ["Photoshop", "Illustrator"],
      "hourly_rate": 30,
      "profile_picture": "https://reqres.in/img/faces/9-image.jpg",
      "isBooked": true
    },
    {
      "id": 3,
      "name": "Bryon Field",
      "email": "byron.fields@reqres.in",
      "password": "password",
      "profession": "Web Developer",
      "skills": ["HTML", "CSS", "JavaScript"],
      "hourly_rate": 25,
      "avatar": "https://reqres.in/img/faces/10-image.jpg",
      "isBooked": false
    }
  ]
}
